README.rst
httpie_oauth.py
setup.py
httpie_oauth.egg-info/PKG-INFO
httpie_oauth.egg-info/SOURCES.txt
httpie_oauth.egg-info/dependency_links.txt
httpie_oauth.egg-info/entry_points.txt
httpie_oauth.egg-info/not-zip-safe
httpie_oauth.egg-info/requires.txt
httpie_oauth.egg-info/top_level.txt