Metadata-Version: 1.1
Name: httpie-oauth
Version: 1.0.1
Summary: OAuth plugin for HTTPie.
Home-page: https://github.com/jkbr/httpie-oauth
Author: Jakub Roztocil
Author-email: jakub@roztocil.name
License: BSD
Download-URL: https://github.com/jkbr/httpie-oauth
Platform: UNKNOWN
Classifier: Development Status :: 5 - Production/Stable
Classifier: Programming Language :: Python
Classifier: Environment :: Plugins
Classifier: License :: OSI Approved :: BSD License
Classifier: Topic :: Internet :: WWW/HTTP
Classifier: Topic :: Utilities
